tugo/__init__.py
tugo/app.py
tugo-0.1.2.dist-info/licenses/LICENSE
tugo-0.1.2.dist-info/METADATA
tugo-0.1.2.dist-info/WHEEL
tugo-0.1.2.dist-info/top_level.txt
tugo-0.1.2.dist-info/RECORD
