Metadata-Version: 2.4
Name: tugo
Version: 0.1.2
Classifier: Programming Language :: Python :: 3
Classifier: License :: OSI Approved :: MIT License
Classifier: Operating System :: OS Independent
Requires-Python: >=3.6
License-File: LICENSE
Requires-Dist: anyio==4.9.0
Requires-Dist: flet==0.27.0
Dynamic: classifier
Dynamic: license-file
Dynamic: requires-dist
Dynamic: requires-python
